reple/__init__.py
reple/reple
reple/reple.py
reple/configs/bcl.json
reple/configs/c.json
reple/configs/cxx.json
reple/configs/dash.json
reple/configs/go.json
reple/configs/mpicc.json
reple/configs/mpicxx.json
reple/configs/nasm.json
reple/configs/rust.json
reple/configs/upc.json
reple/configs/upcxx.json
reple-0.1.0.2.data/scripts/reple
reple-0.1.0.2.dist-info/LICENSE
reple-0.1.0.2.dist-info/METADATA
reple-0.1.0.2.dist-info/WHEEL
reple-0.1.0.2.dist-info/top_level.txt
reple-0.1.0.2.dist-info/RECORD
