Metadata-Version: 2.1
Name: reple
Version: 0.1.0.2
Summary: "replay-based" REPL for compiled languages
Home-page: https://github.com/BenBrock/reple
Author: Benjamin Brock
Author-email: brock@cs.berkeley.edu
License: UNKNOWN
Platform: UNKNOWN
Classifier: Programming Language :: Python :: 3
Classifier: License :: OSI Approved :: BSD License
Classifier: Operating System :: OS Independent
Requires-Dist: prompt-toolkit
Requires-Dist: pygments
